pytoken_zzl/__init__.py
pytoken_zzl/token.py
pytoken_zzl-0.2.0.dist-info/LICENSE.txt
pytoken_zzl-0.2.0.dist-info/METADATA
pytoken_zzl-0.2.0.dist-info/WHEEL
pytoken_zzl-0.2.0.dist-info/top_level.txt
pytoken_zzl-0.2.0.dist-info/RECORD
