Metadata-Version: 2.1
Name: pytoken_zzl
Version: 0.2.0
Summary: A token management library
Author-email: Zilong ZHOU <zzl0712@outlook.com>
Maintainer-email: Zilong ZHOU <zzl0712@outlook.com>
License: Copyright (c) 2016 The Python Packaging Authority (PyPA)
Project-URL: Homepage, https://github.com/adlsdztony/pytoken_zzl
Project-URL: Bug Reports, https://github.com/adlsdztony/pytoken_zzl/issues
Keywords: token,web,cookie
Classifier: Development Status :: 3 - Alpha
Classifier: Intended Audience :: Developers
Classifier: Topic :: Software Development :: Build Tools
Classifier: License :: OSI Approved :: MIT License
Classifier: Programming Language :: Python :: 3
Classifier: Programming Language :: Python :: 3.7
Classifier: Programming Language :: Python :: 3.8
Classifier: Programming Language :: Python :: 3.9
Classifier: Programming Language :: Python :: 3.10
Classifier: Programming Language :: Python :: 3.11
Classifier: Programming Language :: Python :: 3 :: Only
Requires-Python: >=3.7
License-File: LICENSE.txt
Provides-Extra: dev
Requires-Dist: check-manifest ; extra == 'dev'
Provides-Extra: test
Requires-Dist: coverage ; extra == 'test'
